jl95/pytools/base64id.py
jl95/pytools/begonecr.py
jl95/pytools/bodycurl.py
jl95/pytools/diff.py
jl95/pytools/diffdirs.py
jl95/pytools/dircopy.py
jl95/pytools/f.py
jl95/pytools/fcopy.py
jl95/pytools/findfile.py
jl95/pytools/finds.py
jl95/pytools/findsbin.py
jl95/pytools/ftpcopy.py
jl95/pytools/hashdirs.py
jl95/pytools/hashf.py
jl95/pytools/jsonbeau.py
jl95/pytools/jumble.py
jl95/pytools/listdirs.py
jl95/pytools/listvar.py
jl95/pytools/miko.py
jl95/pytools/printfile.py
jl95/pytools/printfilebin.py
jl95/pytools/printfiles.py
jl95/pytools/pwd.py
jl95/pytools/pycdel.py
jl95/pytools/recurse.py
jl95/pytools/swxml.py
jl95/pytools/tcplisten.py
jl95/pytools/tcpt.py
jl95/pytools/tcptalk.py
jl95/pytools/uuidd.py
jl95/pytools/version.py
jl95/pytools/vtpyproject.py
jl95/pytools/wikimaker.py
jl95/pytools/wsclient.py
jl95terceira/pytools/base64id.py
jl95terceira/pytools/begonecr.py
jl95terceira/pytools/bodycurl.py
jl95terceira/pytools/diff.py
jl95terceira/pytools/diffdirs.py
jl95terceira/pytools/dircopy.py
jl95terceira/pytools/f.py
jl95terceira/pytools/fcopy.py
jl95terceira/pytools/findfile.py
jl95terceira/pytools/finds.py
jl95terceira/pytools/findsbin.py
jl95terceira/pytools/ftpcopy.py
jl95terceira/pytools/hashdirs.py
jl95terceira/pytools/hashf.py
jl95terceira/pytools/jsonbeau.py
jl95terceira/pytools/jsonflat.py
jl95terceira/pytools/jumble.py
jl95terceira/pytools/listdirs.py
jl95terceira/pytools/listvar.py
jl95terceira/pytools/miko.py
jl95terceira/pytools/printfile.py
jl95terceira/pytools/printfilebin.py
jl95terceira/pytools/printfiles.py
jl95terceira/pytools/pwd.py
jl95terceira/pytools/pycdel.py
jl95terceira/pytools/tcplisten.py
jl95terceira/pytools/tcpt.py
jl95terceira/pytools/tcptalk.py
jl95terceira/pytools/uuidd.py
jl95terceira/pytools/version.py
jl95terceira/pytools/wikimaker.py
jl95terceira/pytools/wsclient.py
jl95terceira_pytools-1.2.1.dist-info/METADATA
jl95terceira_pytools-1.2.1.dist-info/WHEEL
jl95terceira_pytools-1.2.1.dist-info/entry_points.txt
jl95terceira_pytools-1.2.1.dist-info/RECORD
