Metadata-Version: 2.4
Name: jl95terceira_pytools
Version: 1.2.1
Summary: Python command line tools collection (general)
Project-URL: Homepage, https://github.com/jl95terceira/project-pytools
Project-URL: Issues, https://github.com/jl95terceira/project-pytools/issues
Author-email: Joao Luis Ornelas da Silva <jl95terceira@gmail.com>
Classifier: License :: OSI Approved :: MIT License
Classifier: Operating System :: OS Independent
Classifier: Programming Language :: Python :: 3
Requires-Python: >=3.12
Requires-Dist: bcrypt==5.0.0
Requires-Dist: cffi==2.0.0
Requires-Dist: cryptography==46.0.3
Requires-Dist: invoke==2.2.1
Requires-Dist: jl95terceira-batteries>=1.4.1
Requires-Dist: jl95terceira-pytools-env-git>=0.1.3
Requires-Dist: jl95terceira-pytools-env>=0.2.8
Requires-Dist: paramiko==4.0.0
Requires-Dist: pycparser==2.23
Requires-Dist: pynacl==1.6.0
